[
  {
    "id": "land-2024-01-23-凤凰新村-1",
    "type": "single",
    "title": "凤凰新村",
    "date": "2024-01-23",
    "location": "杭州",
    "category": "L",
    "tags": [
      "城市",
      "街景"
    ],
    "thumbnail": "public/gallery/landscape/24-01/2024-01-23 凤凰新村/thumbnails/1.webp",
    "display": "public/gallery/landscape/24-01/2024-01-23 凤凰新村/display/1.webp"
  },
  {
    "id": "land-2024-01-23-凤凰新村-2",
    "type": "single",
    "title": "凤凰新村",
    "date": "2024-01-23",
    "location": "杭州",
    "category": "L",
    "tags": [
      "城市",
      "街景"
    ],
    "thumbnail": "public/gallery/landscape/24-01/2024-01-23 凤凰新村/thumbnails/2.webp",
    "display": "public/gallery/landscape/24-01/2024-01-23 凤凰新村/display/2.webp"
  },
  {
    "id": "land-2024-01-23-凤凰新村-3",
    "type": "single",
    "title": "凤凰新村",
    "date": "2024-01-23",
    "location": "杭州",
    "category": "L",
    "tags": [
      "城市",
      "街景"
    ],
    "thumbnail": "public/gallery/landscape/24-01/2024-01-23 凤凰新村/thumbnails/3.webp",
    "display": "public/gallery/landscape/24-01/2024-01-23 凤凰新村/display/3.webp"
  }
]